emergenet/__init__.py
emergenet/domseq.py
emergenet/emergenet.py
emergenet/utils.py
emergenet/data/current_subtypes.json
emergenet/data/human.csv.gz
emergenet/data/current/H1.csv
emergenet/data/current/H3.csv
emergenet/data/current/N1.csv
emergenet/data/current/N2.csv
emergenet/models/H1.joblib.gz
emergenet/models/H3.joblib.gz
emergenet/models/N1.joblib.gz
emergenet/models/N2.joblib.gz
emergenet/models/emergence_high_model.joblib
emergenet/models/emergence_low_model.joblib
emergenet/models/emergence_model.joblib
emergenet-0.4.8.dist-info/LICENSE
emergenet-0.4.8.dist-info/METADATA
emergenet-0.4.8.dist-info/WHEEL
emergenet-0.4.8.dist-info/top_level.txt
emergenet-0.4.8.dist-info/RECORD
