Metadata-Version: 2.1
Name: emergenet
Version: 0.4.8
Summary: Superfast Risk Estimation of Emerging Pathogens
Home-page: https://github.com/zeroknowledgediscovery/emergenet
Download-URL: https://github.com/zeroknowledgediscovery/emergenet/archive/0.4.8.tar.gz
Author: zed.uchicago.edu
Author-email: ishanu@uchicago.edu
License: LICENSE
Keywords: computational biology,decision trees,machine learning,emerging pathogens
Classifier: Development Status :: 4 - Beta
Classifier: Intended Audience :: Developers
Classifier: Intended Audience :: Science/Research
Classifier: Topic :: Scientific/Engineering :: Information Analysis
Classifier: Topic :: Software Development :: Libraries
Classifier: Programming Language :: Python :: 3.6
Requires-Python: >=3.6
License-File: LICENSE
Requires-Dist: scikit-learn
Requires-Dist: scipy
Requires-Dist: numpy
Requires-Dist: pandas
Requires-Dist: joblib
Requires-Dist: quasinet (==0.1.54)
Requires-Dist: distance
Requires-Dist: alphashape
